{
  "identifiantArticle" : "https___www.senescoop.net_appel-a-la-priere-dans-les-mosquees-les-precisions-de-la-ligue-des-imams-du-senegal_",
  "urlArticle" : "https://www.senescoop.net/appel-a-la-priere-dans-les-mosquees-les-precisions-de-la-ligue-des-imams-du-senegal/",
  "sourceArticle" : "senescoop",
  "thematiqueArticle" : "Religion",
  "sousCategorieArticle" : "",
  "imagesArticle" : [ "https://www.senescoop.net/wp-content/uploads/2019/10/prieres_0058.jpg" ],
  "titreArticle" : "Appel à la prière dans les mosquées : Les précisions de la ligue des Imams du Sénégal | Senescoop.net",
  "resumeArticle" : "Appel à la prière dans les mosquées : Les précisions de la ligue des Imams du Sénégal",
  "auteurArticle" : "Senescoop",
  "datePublicationArticle" : "2020-03-27T14:04:21+00:00",
  "dateMiseJourArticle" : "2020-03-27T14:04:22+01:00",
  "videosArticle" : [ ],
  "nombreLikesArticle" : 67,
  "nombreLecturesArticle" : 76,
  "nombreCommentairesArticle" : 0,
  "nombrePartagesArticle" : 0,
  "contenuArticle" : "À la suite de sa déclaration du recommandant la suspension des prières du vendredi jusqu’à nouvel ordre pour empêcher la propagation du COVID-19, le bureau exécutif de la Ligue des Imams et Prédicateurs du Sénégal ( Lips) s’est encore réuni ce jeudi pour évaluer la situation et faire les précisions.Selon les collègues de Oustaz Dame Ndiaye, l’interdiction des rassemblements dans les mosquées aux heures d’affluence ne concerne pas les appels à la prière. Les Muezzins sont appelés à faire les appels (Al Azaane – Noodd) pour annoncer l’avènement des heures de prière. Ils précisent qu’ils pourront à cet effet demander aux fidèles de prier dans leurs concessions.La Ligue des imams rappelle à l’ensemble des populations leur devoir citoyen de respect des dispositions prises par les autorités publiques et sanitaires pour contenir la pandémie. Non sans prier “Allah SWT” de répandre sa miséricorde sur le Sénégal, de lui préserver sa paix et sa stabilité, ainsi que pour l’ensemble des pays de la Ummah et de l’humanité toute entière.des prières du vendredi jusqu’à nouvel ordre pour empêcher la propagation du COVID 19 , le bureau exécutif de la Ligue des Imams et Prédicateurs du Sénégal ( Lips) s’est encore réuni ce jeudi pour évaluer la situation et faire les précisions.Selon les collègues de Oustaz Dame Ndiaye, l’interdiction des rassemblements dans les mosquées aux heures d’affluence ne concerne pas les appels à la prière. Les Muezzins sont appelés à faire les appels (Al Azaane – Noodd) pour annoncer l’avènement des heures de prière. Ils précisent qu’ils pourront à cet effet demander aux fidèles de prier dans leurs concessions.La Ligue des imams rappelle à l’ensemble des populations leur devoir citoyen de respect des dispositions prises par les autorités publiques et sanitaires pour contenir la pandémie. Non sans prier “Allah SWT” de répandre sa miséricorde sur le Sénégal, de lui préserver sa paix et sa stabilité, ainsi que pour l’ensemble des pays de la Ummah et de l’humanité toute entière.",
  "commentairesArticle" : [ ],
  "dateCollecteArticle" : "Tue Apr 07 06:53:40 GMT 2020",
  "motsClesArticle" : ""
}